setup.py
pytkcon/__init__.py
pytkcon/pytkcon.py
pytkcon/tk_app_example.py
pytkcon/tk_console.py
pytkcon.egg-info/PKG-INFO
pytkcon.egg-info/SOURCES.txt
pytkcon.egg-info/dependency_links.txt
pytkcon.egg-info/not-zip-safe
pytkcon.egg-info/top_level.txt