Metadata-Version: 1.0
Name: pytkcon
Version: 1.0
Summary: Tkinter Console Widget Class
Home-page: http://github.com/samyzaf/pytkcon
Author: Samy Zafrany
Author-email: admin@samyzaf.com
License: MIT
Platform: UNKNOWN
